flag_gen.py
main.py
dbdth25_pip_install_or_pypi-0.1.1.dist-info/METADATA
dbdth25_pip_install_or_pypi-0.1.1.dist-info/WHEEL
dbdth25_pip_install_or_pypi-0.1.1.dist-info/entry_points.txt
dbdth25_pip_install_or_pypi-0.1.1.dist-info/top_level.txt
dbdth25_pip_install_or_pypi-0.1.1.dist-info/RECORD
