Metadata-Version: 2.4
Name: dbdth25-pip_install_or_pypi
Version: 0.1.1
Summary: Databased Hack&Seek 2025 problem: pip_install_or_pypi
Author: AnirudhG07
Requires-Python: >=3.8
